jinyu_utils/__init__.py
jinyu_utils/jinyu_dataset.py
jinyu_utils/jinyu_inspect.py
jinyu_utils/jinyu_inspect_file.py
jinyu_utils/jinyu_preprocess_wiki.py
jinyu_utils/jinyu_tokenizer.py
jinyu_utils-0.1.0.dist-info/licenses/LICENSE
jinyu_utils-0.1.0.dist-info/METADATA
jinyu_utils-0.1.0.dist-info/WHEEL
jinyu_utils-0.1.0.dist-info/top_level.txt
jinyu_utils-0.1.0.dist-info/RECORD
