Metadata-Version: 2.4
Name: jinyu_utils
Version: 0.1.0
Summary: One-line summary
Author-email: Yukai Jin <fish1928@outlook.com>
License: MIT License
Project-URL: Homepage, https://github.com/fish1928/jinyu_utils
Classifier: License :: OSI Approved :: MIT License
Requires-Python: >=3.9
License-File: LICENSE
Dynamic: license-file
